json_source_map/__init__.py
json_source_map/advance.py
json_source_map/check.py
json_source_map/constants.py
json_source_map/errors.py
json_source_map/handle.py
json_source_map/types.py
json_source_map-1.0.4.dist-info/LICENSE
json_source_map-1.0.4.dist-info/WHEEL
json_source_map-1.0.4.dist-info/METADATA
json_source_map-1.0.4.dist-info/RECORD
