Metadata-Version: 2.1
Name: json-source-map
Version: 1.0.4
Summary: Calculate the source map for a JSON document.
Home-page: https://github.com/open-alchemy/json-source-map/wiki
Keywords: Python,JSON,source map
Author: David Andersson
Author-email: nderssonpublic@gmail.com
Requires-Python: >=3.8,<4.0
Classifier: Development Status :: 5 - Production/Stable
Classifier: License :: OSI Approved :: Apache Software License
Classifier: Natural Language :: English
Classifier: Operating System :: OS Independent
Classifier: Programming Language :: Python :: 3
Classifier: Programming Language :: Python :: 3.10
Classifier: Programming Language :: Python :: 3.8
Classifier: Programming Language :: Python :: 3.9
Classifier: Topic :: Software Development :: Disassemblers
Classifier: Topic :: Software Development :: Documentation
Classifier: Topic :: Text Processing
Classifier: Topic :: Utilities
Classifier: Typing :: Typed
Project-URL: Documentation, https://github.com/open-alchemy/json-source-map/wiki
Project-URL: Repository, https://github.com/open-alchemy/json-source-map
